dataforge_ds/__init__.py
dataforge_ds/cli.py
dataforge_ds-0.2.1.dist-info/METADATA
dataforge_ds-0.2.1.dist-info/WHEEL
dataforge_ds-0.2.1.dist-info/entry_points.txt
dataforge_ds-0.2.1.dist-info/RECORD
