Metadata-Version: 2.1
Name: dataforge-ds
Version: 0.2.1
Summary: CLI tool for managing Python project templates.
License: MIT
Author: Danijel S.
Requires-Python: >=3.10,<4.0
Classifier: License :: OSI Approved :: MIT License
Classifier: Programming Language :: Python :: 3
Classifier: Programming Language :: Python :: 3.10
Classifier: Programming Language :: Python :: 3.11
Classifier: Programming Language :: Python :: 3.12
Requires-Dist: click (>=8.1.3,<9.0.0)
Requires-Dist: copier (>=6.1.0,<7.0.0)
Requires-Dist: pyspark (>=3.3.1,<4.0.0)
